{
    "Logos" : [
        {
            "img": "/images/Logos/1.webp"
        },
        {
            "img": "/images/Logos/2.webp"
        },
        {
            "img": "/images/Logos/3.webp"
        },
        {
            "img": "/images/Logos/4.webp"
        },
        {
            "img": "/images/Logos/5.webp"
        },
        {
            "img": "/images/Logos/6.webp"
        },
        {
            "img": "/images/Logos/7.webp"
        },
        {
            "img": "/images/Logos/8.webp"
        },
        {
            "img": "/images/Logos/9.webp"
        },
        {
            "img": "/images/Logos/10.webp"
        },
        {
            "img": "/images/Logos/11.webp"
        },
        {
            "img": "/images/Logos/12.webp"
        }
    ]
}